ejtp-0.9.7p1.data/scripts/ejtp-keygen
ejtp-0.9.7p1.data/scripts/ejtp-console
ejtp-0.9.7p1.data/scripts/ejtp-identity
ejtp-0.9.7p1.data/scripts/ejtpd
ejtp-0.9.7p1.data/scripts/ejtp-crypto
ejtp-0.9.7p1.dist-info/RECORD
ejtp-0.9.7p1.dist-info/METADATA
ejtp-0.9.7p1.dist-info/WHEEL
ejtp-0.9.7p1.dist-info/pydist.json
ejtp-0.9.7p1.dist-info/top_level.txt
ejtp-0.9.7p1.dist-info/DESCRIPTION.rst
ejtp/__init__.py
ejtp/client.py
ejtp/address.py
ejtp/router.py
ejtp/config.py
ejtp/identity/__init__.py
ejtp/identity/core.py
ejtp/identity/cache.py
ejtp/identity/ref.py
ejtp/util/compat.py
ejtp/util/__init__.py
ejtp/util/py2and3.py
ejtp/util/scripts.py
ejtp/util/crashnicely.py
ejtp/util/hasher.py
ejtp/tests/test_address.py
ejtp/tests/test_py2and3.py
ejtp/tests/tools.py
ejtp/tests/test_compressed_frame.py
ejtp/tests/__init__.py
ejtp/tests/test_crypto.py
ejtp/tests/runner.py
ejtp/tests/test_identity.py
ejtp/tests/resource_path.py
ejtp/tests/test_scripts.py
ejtp/tests/test_router.py
ejtp/tests/examplecache.json
ejtp/tests/test_client.py
ejtp/tests/test_frames.py
ejtp/tests/test_util.py
ejtp/tests/test_script_utils.py
ejtp/tests/test_config.py
ejtp/tests/test_jacks.py
ejtp/tests/idents/philip@ri.hype
ejtp/tests/idents/jonathan@matrix.hype
ejtp/crypto/__init__.py
ejtp/crypto/encryptor.py
ejtp/crypto/aes.py
ejtp/crypto/rsa.py
ejtp/crypto/ecc.py
ejtp/crypto/rotate.py
ejtp/frame/registration.py
ejtp/frame/__init__.py
ejtp/frame/encrypted.py
ejtp/frame/signed.py
ejtp/frame/json.py
ejtp/frame/base.py
ejtp/frame/address.py
ejtp/frame/compressed.py
ejtp/applications/__init__.py
ejtp/applications/motd.py
ejtp/applications/daemon.py
ejtp/applications/ejforward/__init__.py
ejtp/applications/ejforward/server.py
ejtp/applications/ejforward/client.py
ejtp/jacks/__init__.py
ejtp/jacks/core.py
ejtp/jacks/udp.py
ejtp/jacks/stream.py
ejtp/jacks/tcp.py
ejtp/vendor/__init__.py
ejtp/vendor/docopt.py
