Metadata-Version: 2.0
Name: ejtp
Version: 0.9.7p1
Summary: Encrypted JSON Transport Protocol library
Home-page: https://github.com/campadrenalin/EJTP-lib-python/
Author: Philip Horger
Author-email: philip.horger@gmail.com
License: UNKNOWN
Platform: UNKNOWN
Classifier: Development Status :: 4 - Beta
Classifier: License :: OSI Approved :: GNU Library or Lesser General Public License (LGPL)
Classifier: Environment :: Console
Classifier: Programming Language :: Python
Classifier: Programming Language :: Python :: 2.6
Classifier: Programming Language :: Python :: 2.7
Classifier: Programming Language :: Python :: 3
Classifier: Programming Language :: Python :: 3.2
Classifier: Programming Language :: Python :: 3.3
Classifier: Operating System :: MacOS :: MacOS X
Classifier: Operating System :: Microsoft :: Windows
Classifier: Operating System :: POSIX
Classifier: Intended Audience :: Developers
Classifier: Topic :: Communications
Classifier: Topic :: Internet
Classifier: Topic :: Security :: Cryptography
Requires-Dist: pycrypto
Requires-Dist: persei
Requires-Dist: requests
Requires-Dist: streql
